colcon_top_level_workspace/__init__.py
colcon_top_level_workspace/argument_parser.py
colcon_top_level_workspace-0.1.0.dist-info/licenses/LICENSE
colcon_top_level_workspace-0.1.0.dist-info/METADATA
colcon_top_level_workspace-0.1.0.dist-info/WHEEL
colcon_top_level_workspace-0.1.0.dist-info/entry_points.txt
colcon_top_level_workspace-0.1.0.dist-info/top_level.txt
colcon_top_level_workspace-0.1.0.dist-info/zip-safe
colcon_top_level_workspace-0.1.0.dist-info/RECORD
