Metadata-Version: 2.4
Name: colcon-top-level-workspace
Version: 0.1.0
Summary: Extension for colcon to locate and use a top-level workspace
Home-page: https://colcon.readthedocs.io
Author: Robert Haschke
Author-email: rhaschke@techfak.uni-bielefeld.de
License: Apache License, Version 2.0
Project-URL: GitHub, https://github.com/rhaschke/colcon-top-level-workspace
Keywords: colcon
Classifier: Development Status :: 3 - Alpha
Classifier: Environment :: Plugins
Classifier: Intended Audience :: Developers
Classifier: License :: OSI Approved :: Apache Software License
Classifier: Operating System :: MacOS
Classifier: Operating System :: POSIX
Classifier: Programming Language :: Python
Classifier: Topic :: Software Development :: Build Tools
Requires-Python: >=3.6
License-File: LICENSE
Requires-Dist: colcon-core>=0.13.0
Provides-Extra: test
Requires-Dist: flake8<6,>=3.6.0; extra == "test"
Requires-Dist: flake8-blind-except; extra == "test"
Requires-Dist: flake8-builtins; extra == "test"
Requires-Dist: flake8-class-newline; extra == "test"
Requires-Dist: flake8-comprehensions; extra == "test"
Requires-Dist: flake8-deprecated; extra == "test"
Requires-Dist: flake8-docstrings; extra == "test"
Requires-Dist: flake8-import-order; extra == "test"
Requires-Dist: flake8-quotes; extra == "test"
Requires-Dist: pep8-naming; extra == "test"
Requires-Dist: pylint; extra == "test"
Requires-Dist: pytest; extra == "test"
Requires-Dist: pytest-cov; extra == "test"
Requires-Dist: scspell3k>=2.2; extra == "test"
Dynamic: license-file
